pytest_pickle_cache/__init__.py
pytest_pickle_cache/plugin.py
pytest_pickle_cache-0.1.2.dist-info/METADATA
pytest_pickle_cache-0.1.2.dist-info/WHEEL
pytest_pickle_cache-0.1.2.dist-info/entry_points.txt
pytest_pickle_cache-0.1.2.dist-info/licenses/LICENSE
pytest_pickle_cache-0.1.2.dist-info/RECORD
