Metadata-Version: 2.4
Name: pytest-pickle-cache
Version: 0.1.2
Summary: A pytest plugin for caching test results using pickle.
Project-URL: Documentation, https://github.com/daizutabi/pytest-pickle-cache
Project-URL: Source, https://github.com/daizutabi/pytest-pickle-cache
Project-URL: Issues, https://github.com/daizutabi/pytest-pickle-cache/issues
Author-email: daizutabi <daizutabi@gmail.com>
License: MIT License
License-File: LICENSE
Classifier: Framework :: Pytest
Classifier: Intended Audience :: Developers
Classifier: License :: OSI Approved :: MIT License
Classifier: Programming Language :: Python
Classifier: Programming Language :: Python :: 3.10
Classifier: Programming Language :: Python :: 3.11
Classifier: Programming Language :: Python :: 3.12
Classifier: Programming Language :: Python :: 3.13
Classifier: Topic :: Software Development :: Testing
Requires-Python: >=3.10
Requires-Dist: pytest>=7
